__init__.py
main.py
parser.py
latency_scout-0.0.3.dist-info/LICENSE
latency_scout-0.0.3.dist-info/METADATA
latency_scout-0.0.3.dist-info/WHEEL
latency_scout-0.0.3.dist-info/entry_points.txt
latency_scout-0.0.3.dist-info/top_level.txt
latency_scout-0.0.3.dist-info/RECORD
