Metadata-Version: 2.1
Name: latency-scout
Version: 0.0.3
Summary: A highly accurate tool to assess the latency of crypto exchange websocket data feeds.
Author-email: Daniel Molenaars <daniel.molenaars@alibaba-inc.com>
License:                                  Apache License
Keywords: crypto exchange,latency,tester
Requires-Python: >=3.9
License-File: LICENSE
Requires-Dist: ccxt==4.4.29
Requires-Dist: sslkeylog
Requires-Dist: numpy
Requires-Dist: prettytable
Requires-Dist: pyshark
Requires-Dist: aiohttp==3.10
Requires-Dist: tqdm
